[
    {
        "Q": "What are the games that you shared with me that were fun?"
    },
    {
        "Q": "Which movies did you share with me?"
    },
    {
        "Q": "On April 30th, we talked a lot. What topics did we talk about?"
    },
    {
        "Q": "On May 2nd, I was very upset. What caused my distress?"
    },
    {
        "Q": "I once consulted you on how to improve my programming efficiency. What advice did you give me?"
    },
    {
        "Q": "What outdoor sports do I enjoy?"
    }
]
